pyscisci/__init__.py
pyscisci/all.py
pyscisci/database.py
pyscisci/embedding.py
pyscisci/filter.py
pyscisci/network.py
pyscisci/nlp.py
pyscisci/sparsenetworkutils.py
pyscisci/utils.py
pyscisci/visualization.py
pyscisci/datasource/APS.py
pyscisci/datasource/CustomDB.py
pyscisci/datasource/DBLP.py
pyscisci/datasource/MAG.py
pyscisci/datasource/OpenAlex.py
pyscisci/datasource/PubMed.py
pyscisci/datasource/WOS.py
pyscisci/datasource/__init__.py
pyscisci/datasource/readwrite.py
pyscisci/methods/__init__.py
pyscisci/methods/author.py
pyscisci/methods/careertopics.py
pyscisci/methods/cindex.py
pyscisci/methods/creditshare.py
pyscisci/methods/diffusionscientificcredit.py
pyscisci/methods/disruption.py
pyscisci/methods/diversity.py
pyscisci/methods/hindex.py
pyscisci/methods/hotstreak.py
pyscisci/methods/journal.py
pyscisci/methods/longtermimpact.py
pyscisci/methods/netnormcite.py
pyscisci/methods/novelty.py
pyscisci/methods/pivotscore.py
pyscisci/methods/productivitytrajectory.py
pyscisci/methods/publication.py
pyscisci/methods/qfactor.py
pyscisci/methods/raostirling.py
pyscisci/methods/referencestrength.py
pyscisci/methods/sleepingbeauty.py
pyscisci/methods/topicsimilarity.py
pyscisci/tests/__init__.py
pyscisci/tests/test_utils.py
pyscisci-0.92.dist-info/LICENSE
pyscisci-0.92.dist-info/METADATA
pyscisci-0.92.dist-info/WHEEL
pyscisci-0.92.dist-info/top_level.txt
pyscisci-0.92.dist-info/RECORD
